napari_hsi_analysis/_version.py
napari_hsi_analysis/_widget_Fusion.py
napari_hsi_analysis/_widget_Label.py
napari_hsi_analysis/_widget_PCA.py
napari_hsi_analysis/_widget_SiVM.py
napari_hsi_analysis/_widget_UMAP.py
napari_hsi_analysis/_widgets_DataManager.py
napari_hsi_analysis/main.py
napari_hsi_analysis/napari.yaml
napari_hsi_analysis/_tests/__init__.py
napari_hsi_analysis/_tests/test_widget.py
napari_hsi_analysis/modules/D_illuminants.mat
napari_hsi_analysis/modules/data.py
napari_hsi_analysis/modules/functions.py
napari_hsi_analysis/modules/plot_widget.py
napari_hsi_analysis-0.3.1.dist-info/licenses/LICENSE
napari_hsi_analysis-0.3.1.dist-info/METADATA
napari_hsi_analysis-0.3.1.dist-info/WHEEL
napari_hsi_analysis-0.3.1.dist-info/entry_points.txt
napari_hsi_analysis-0.3.1.dist-info/top_level.txt
napari_hsi_analysis-0.3.1.dist-info/RECORD
