Metadata-Version: 2.4
Name: napari-hsi-analysis
Version: 0.3.1
Summary: Napari plugin to perform analysis on Hyperspectral Imaging datasets.
Author: Alessia Di Benedetto
Author-email: alessiadibenedetto.97@gmail.com
License: 
Project-URL: Bug Tracker, https://github.com/alessiadb/napari-hsi-analysis/issues
Project-URL: Documentation, https://github.com/alessiadb/napari-hsi-analysis#README.md
Project-URL: Source Code, https://github.com/alessiadb/napari-hsi-analysis
Project-URL: User Support, https://github.com/alessiadb/napari-hsi-analysis/issues
Classifier: Development Status :: 2 - Pre-Alpha
Classifier: Framework :: napari
Classifier: Intended Audience :: Developers
Classifier: License :: OSI Approved :: BSD License
Classifier: Operating System :: OS Independent
Classifier: Programming Language :: Python
Classifier: Programming Language :: Python :: 3
Classifier: Programming Language :: Python :: 3 :: Only
Classifier: Programming Language :: Python :: 3.10
Classifier: Programming Language :: Python :: 3.11
Classifier: Programming Language :: Python :: 3.12
Classifier: Programming Language :: Python :: 3.13
Classifier: Topic :: Scientific/Engineering :: Image Processing
Requires-Python: >=3.10
License-File: LICENSE
Requires-Dist: numpy
Requires-Dist: magicgui
Requires-Dist: qtpy
Requires-Dist: scikit-image
Requires-Dist: scikit-learn
Requires-Dist: h5py
Requires-Dist: bokeh
Requires-Dist: plotly
Requires-Dist: PyWavelets
Requires-Dist: scipy
Requires-Dist: pyqtgraph
Requires-Dist: qtawesome
Requires-Dist: matplotlib
Requires-Dist: umap-learn
Requires-Dist: spectral
Provides-Extra: testing
Requires-Dist: tox; extra == "testing"
Requires-Dist: pytest; extra == "testing"
Requires-Dist: pytest-cov; extra == "testing"
Requires-Dist: pytest-qt; extra == "testing"
Requires-Dist: napari; extra == "testing"
Requires-Dist: pyqt5; extra == "testing"
Requires-Dist: numpy; extra == "testing"
Requires-Dist: magicgui; extra == "testing"
Requires-Dist: qtpy; extra == "testing"
Requires-Dist: scikit-image; extra == "testing"
Requires-Dist: scikit-learn; extra == "testing"
Requires-Dist: h5py; extra == "testing"
Requires-Dist: bokeh; extra == "testing"
Requires-Dist: plotly; extra == "testing"
Requires-Dist: PyWavelets; extra == "testing"
Requires-Dist: scipy; extra == "testing"
Requires-Dist: pyqtgraph; extra == "testing"
Requires-Dist: qtawesome; extra == "testing"
Requires-Dist: matplotlib; extra == "testing"
Requires-Dist: umap-learn; extra == "testing"
Requires-Dist: spectral; extra == "testing"
Dynamic: license-file
